README.md
setup.py
gretis/__init__.py
gretis/async_cluster_connection.py
gretis/async_connection.py
gretis/exceptions.py
gretis.egg-info/PKG-INFO
gretis.egg-info/SOURCES.txt
gretis.egg-info/dependency_links.txt
gretis.egg-info/not-zip-safe
gretis.egg-info/requires.txt
gretis.egg-info/top_level.txt